[{"id":1405111187,"name":"Better Days","dt":187918,"ar":{"id":1132987,"name":"Arman Cekin"},"al":{"id":83569827,"name":"Better Days","picUrl":"https://p2.music.126.net/unOX2cGUNf4d4g4IwoUv3A==/109951165064032142.jpg"}},{"id":1849954090,"name":"Remember The Summer (feat. Karra)","dt":170624,"ar":{"id":711465,"name":"Ummet Ozcan"},"al":{"id":128371687,"name":"Remember The Summer (feat. Karra)","picUrl":"https://p1.music.126.net/Hw7z_EmuMjPzLJib_SQcwQ==/109951166053385955.jpg"}},{"id":1429604070,"name":"Constellation","dt":172804,"ar":{"id":824107,"name":"Far Out"},"al":{"id":86368314,"name":"Constellation","picUrl":"https://p1.music.126.net/P-9GipJNsfHHwESM3rh6Zg==/109951164787300857.jpg"}},{"id":447076194,"name":"Make Me Move","dt":197052,"ar":{"id":1049930,"name":"Culture Code"},"al":{"id":35051295,"name":"Make Me Move","picUrl":"https://p2.music.126.net/c-meZh9S4qMb8ffqaqGdwA==/109951163371293163.jpg"}},{"id":862100907,"name":"On My Own","dt":270224,"ar":{"id":824107,"name":"Far Out"},"al":{"id":71613868,"name":"On My Own","picUrl":"https://p1.music.126.net/2uPQgxLJSqwCSzxFUjTO5g==/109951163381978198.jpg"}},{"id":1306597651,"name":"Skin 2 Skin","dt":189936,"ar":{"id":806218,"name":"Diamond Pistols"},"al":{"id":72803222,"name":"Skin 2 Skin","picUrl":"https://p2.music.126.net/WsdXqVXwoLXKlFCaXe9YZA==/109951165984737151.jpg"}},{"id":473571249,"name":"Smoke and Fire","dt":196261,"ar":{"id":364737,"name":"Cuebrick"},"al":{"id":35420066,"name":"Smoke and Fire","picUrl":"https://p2.music.126.net/eJpokQyWdZJjZj0_o3p9uQ==/18633423557793032.jpg"}},{"id":1299557506,"name":"Truest Lies (BEAUZ Remix)","dt":185626,"ar":{"id":824107,"name":"Far Out"},"al":{"id":72073088,"name":"Truest Lies","picUrl":"https://p2.music.126.net/ugmok2VUM6c7KuZ_4ceiUA==/109951163448133625.jpg"}},{"id":419250516,"name":"Quicksand","dt":217500,"ar":{"id":290025,"name":"Feenixpawl"},"al":{"id":34750020,"name":"Quicksand","picUrl":"https://p1.music.126.net/t6US_Q_BG7UMpo8xBqfNtw==/1393081244481047.jpg"}},{"id":1832023066,"name":"Where My Heart Goes (feat. KARRA)","dt":181333,"ar":{"id":12203566,"name":"AMIDY"},"al":{"id":125049673,"name":"Where My Heart Goes (feat. KARRA)","picUrl":"https://p2.music.126.net/YpmDOlAawRvGIuQylnppjg==/109951165986641087.jpg"}},{"id":1302084524,"name":"Distraction","dt":234840,"ar":{"id":784373,"name":"Synchronice"},"al":{"id":72302983,"name":"Distraction","picUrl":"https://p1.music.126.net/uRn8Ee5_iJNfABBstknB2A==/109951163469805004.jpg"}},{"id":1436385075,"name":"Survival","dt":201242,"ar":{"id":191581,"name":"Luke Bond"},"al":{"id":87320851,"name":"Survival","picUrl":"https://p1.music.126.net/-w9DPKIX5CzY-XVNLGsRJQ==/109951164859242452.jpg"}},{"id":1398699606,"name":"Silver Lining (feat. KARRA)","dt":214736,"ar":{"id":1132078,"name":"ARMNHMR"},"al":{"id":82660858,"name":"Silver Lining (feat. KARRA)","picUrl":"https://p2.music.126.net/6iSw3uBJ1dCzlA3qRUf59w==/109951164482303815.jpg"}},{"id":573518552,"name":"Into You","dt":244151,"ar":{"id":906123,"name":"Jason Ross"},"al":{"id":39713838,"name":"Into You","picUrl":"https://p1.music.126.net/e3sUoC_3fMA4Rv0eRWkz0w==/109951163783224782.jpg"}},{"id":417247489,"name":"Where We Are (Radio Edit)","dt":243750,"ar":{"id":1053137,"name":"Ryos"},"al":{"id":34739230,"name":"Where We Are","picUrl":"https://p1.music.126.net/IQTWE9xyHgsJAieCcS3j3Q==/109951164334619879.jpg"}},{"id":1341924019,"name":"Into The Light","dt":201340,"ar":{"id":12035151,"name":"Notaker"},"al":{"id":75321386,"name":"Into The Light","picUrl":"https://p2.music.126.net/w5PZH5C488Z1sdUGLQheFQ==/109951163815749284.jpg"}},{"id":470573583,"name":"What It Looks Like","dt":196874,"ar":{"id":1163065,"name":"Daniel Garrick"},"al":{"id":35347092,"name":"What It Looks Like","picUrl":"https://p1.music.126.net/sA-mazPXpTaEzhH-cp06XQ==/109951166277744779.jpg"}},{"id":486814261,"name":"Silent Skies","dt":246677,"ar":{"id":44204,"name":"Seven Lions"},"al":{"id":35578313,"name":"Where I Won't Be Found","picUrl":"https://p1.music.126.net/hRMPijlACQYvsPfjQ1cbCQ==/109951163834726503.jpg"}},{"id":1336866627,"name":"Coincidence","dt":186352,"ar":{"id":1049930,"name":"Culture Code"},"al":{"id":75017991,"name":"Coincidence","picUrl":"https://p2.music.126.net/JirUqrQPSqc2wn65cqt7BA==/109951164989697949.jpg"}},{"id":445153337,"name":"Melody","dt":215812,"ar":{"id":29252,"name":"Ashley Wallbridge"},"al":{"id":35022832,"name":"Electric For Life 2016","picUrl":"https://p1.music.126.net/xhhbranR18kJZP2ad-R1Jw==/109951163180546772.jpg"}},{"id":1341919894,"name":"Comfort Zone ","dt":209474,"ar":{"id":12914324,"name":"S1LVA"},"al":{"id":75320152,"name":"Comfort Zone","picUrl":"https://p1.music.126.net/BtRi5dpikydPjkc2IAvtTg==/109951163815724843.jpg"}},{"id":1371123422,"name":"Revolution","dt":196846,"ar":{"id":27621,"name":"Armin van Buuren"},"al":{"id":79720424,"name":"Revolution","picUrl":"https://p1.music.126.net/xPnjrqKNJaOOV8H6oZbGyQ==/109951164189751509.jpg"}},{"id":1331733157,"name":"Midnight Magic","dt":185391,"ar":{"id":806218,"name":"Diamond Pistols"},"al":{"id":74800458,"name":"Midnight Magic","picUrl":"https://p1.music.126.net/kAV7su-Rvh7210z1jhww6A==/109951165985381470.jpg"}},{"id":1461515292,"name":"Nobody Else","dt":207407,"ar":{"id":1190100,"name":"NONSENS"},"al":{"id":92171938,"name":"Nobody Else","picUrl":"https://p2.music.126.net/uuzUS3MterNqDQDLMfULmQ==/109951165124587568.jpg"}},{"id":404744013,"name":"Platinum Hearts (Suspect 44 Remix)","dt":301500,"ar":{"id":88214,"name":"Breathe Carolina"},"al":{"id":34525010,"name":"Platinum Hearts (Remixes)","picUrl":"https://p2.music.126.net/HJROiZp-cFbZaTgrK9UDtA==/109951163128939534.jpg"}},{"id":440403636,"name":"Before You","dt":212610,"ar":{"id":44458,"name":"The Ready Set"},"al":{"id":34923660,"name":"Before You","picUrl":"https://p2.music.126.net/DxzZloe0P8s2cUqLyTk4pg==/18691697673292466.jpg"}},{"id":413834391,"name":"Searching For You (Original Mix)","dt":201351,"ar":{"id":860945,"name":"Unlike Pluto"},"al":{"id":34702511,"name":"Searching For You","picUrl":"https://p2.music.126.net/0rsUYZ8Ye-IZMJklu8pAHA==/1384285147775659.jpg"}},{"id":461518830,"name":"Chardonnay","dt":208750,"ar":{"id":1063229,"name":"Conro"},"al":{"id":35211160,"name":"Chardonnay","picUrl":"https://p2.music.126.net/ASsOFAa_ld7ZR1mkqNpsBQ==/109951163311453017.jpg"}},{"id":463001856,"name":"Undiscovered","dt":207827,"ar":{"id":29252,"name":"Ashley Wallbridge"},"al":{"id":35235189,"name":"Undiscovered","picUrl":"https://p1.music.126.net/1K4rayLBp5Otzu71nV3xQg==/109951163132614453.jpg"}},{"id":1351253920,"name":"Nothing To Hide (feat. Karra)","dt":218689,"ar":{"id":776627,"name":"Boombox Cartel"},"al":{"id":75817678,"name":"Nothing To Hide","picUrl":"https://p1.music.126.net/lBMf7tsUCe0y31_Xa_-88Q==/109951164905370327.jpg"}},{"id":466795335,"name":"Let Me Go","dt":232109,"ar":{"id":851710,"name":"Paris Blohm"},"al":{"id":35293300,"name":"Let Me Go (feat. KARRA)","picUrl":"https://p1.music.126.net/gA1qZuTLi01ngluVqq0TjA==/18556457743814379.jpg"}},{"id":444548460,"name":"Ice (feat. Karra)","dt":205061,"ar":{"id":135253,"name":"Jackal"},"al":{"id":35023579,"name":"Ice","picUrl":"https://p1.music.126.net/XS4JcE68yYfLySL58B4VeQ==/109951163378945041.jpg"}},{"id":1419361979,"name":"Anything","dt":215190,"ar":{"id":11986023,"name":"Palm Tree Gang"},"al":{"id":85277052,"name":"Anything","picUrl":"https://p1.music.126.net/suDUqFUAUg_NKWNmrRnGGQ==/109951164659291626.jpg"}},{"id":487587909,"name":"Break Me","dt":222631,"ar":{"id":954338,"name":"Trivecta"},"al":{"id":35644274,"name":"Rocket League x Monstercat Vol. 1","picUrl":"https://p1.music.126.net/CyYEtjKdWGKbwzLwgHhDJw==/109951163311492600.jpg"}},{"id":1342702541,"name":"Take It All","dt":269696,"ar":{"id":12000027,"name":"Kompany"},"al":{"id":75357116,"name":"Metropolis EP","picUrl":"https://p1.music.126.net/h6McJF8WMowu2999mFU-Lw==/109951164035764565.jpg"}},{"id":445702267,"name":"Traces (Original Mix)","dt":210285,"ar":{"id":1182277,"name":"APEK"},"al":{"id":35042055,"name":"Traces","picUrl":"https://p1.music.126.net/gkzqHKxLgVDqDISuQ4_ltQ==/109951164334634312.jpg"}},{"id":863493627,"name":"Paradigm","dt":191250,"ar":{"id":12647410,"name":"Bad Computer"},"al":{"id":71705537,"name":"Paradigm","picUrl":"https://p1.music.126.net/VfNjM8sWCu1kQQNFul78oA==/109951163381975411.jpg"}},{"id":1493495874,"name":"Sweet Dreams (Are Made of This)","dt":162525,"ar":{"id":76928,"name":"Smack"},"al":{"id":97995858,"name":"Sweet Dreams (Are Made of This)","picUrl":"https://p2.music.126.net/VnOUXkVb5ZfGmauf8ZaBwg==/109951165446724313.jpg"}},{"id":536622896,"name":"Lost","dt":216008,"ar":{"id":12262174,"name":"Sinner's Heist"},"al":{"id":37579189,"name":"Lost","picUrl":"https://p2.music.126.net/4mVS1SsMlvMSC-m6E0x1zg==/109951163164848149.jpg"}},{"id":453268789,"name":"More Than I Can Take","dt":262549,"ar":{"id":737112,"name":"LOUDPVCK"},"al":{"id":35123387,"name":"More Than I Can Take","picUrl":"https://p2.music.126.net/57SJqJdy4yK5-KkVXuyoyg==/109951163304305235.jpg"}},{"id":411907885,"name":"Revolve","dt":164000,"ar":{"id":383374,"name":"Carl Nunes"},"al":{"id":34685588,"name":"Revolve","picUrl":"https://p2.music.126.net/rnn0V2oHsAhkAoBBiFZfUg==/109951163128925462.jpg"}},{"id":511921290,"name":"Who I Am (Original Mix)","dt":305005,"ar":{"id":12035151,"name":"Notaker"},"al":{"id":36451493,"name":"Who I Am","picUrl":"https://p2.music.126.net/JNR7_Gfij9yYFMA2mIJqiw==/109951163039958542.jpg"}}]