[{"id":40157302,"name":"Tech Noir","dt":297432,"ar":{"id":1124210,"name":"GUNSHIP"},"al":{"id":3439370,"name":"GUNSHIP","picUrl":"https://p2.music.126.net/5cpUzAuspDNqn5yeKl3uVA==/109951163787117752.jpg"}},{"id":40157300,"name":"The Mountain","dt":264410,"ar":{"id":1124210,"name":"GUNSHIP"},"al":{"id":3439370,"name":"GUNSHIP","picUrl":"https://p1.music.126.net/5cpUzAuspDNqn5yeKl3uVA==/109951163787117752.jpg"}},{"id":40157308,"name":"Fly for Your Life","dt":279170,"ar":{"id":1124210,"name":"GUNSHIP"},"al":{"id":3439370,"name":"GUNSHIP","picUrl":"https://p1.music.126.net/5cpUzAuspDNqn5yeKl3uVA==/109951163787117752.jpg"}},{"id":40157311,"name":"Revel in Your Time (Miami Nights 1984 Remix)","dt":251076,"ar":{"id":1124210,"name":"GUNSHIP"},"al":{"id":3439370,"name":"GUNSHIP","picUrl":"https://p2.music.126.net/5cpUzAuspDNqn5yeKl3uVA==/109951163787117752.jpg"}},{"id":1333142659,"name":"The Video Game Champion","dt":255180,"ar":{"id":1124210,"name":"GUNSHIP"},"al":{"id":74870142,"name":"The Video Game Champion","picUrl":"https://p1.music.126.net/GVf_ayNJGE3LsRNJ0ycGyQ==/109951163723194939.jpg"}},{"id":40157309,"name":"Maximum Black","dt":339543,"ar":{"id":1124210,"name":"GUNSHIP"},"al":{"id":3439370,"name":"GUNSHIP","picUrl":"https://p1.music.126.net/5cpUzAuspDNqn5yeKl3uVA==/109951163787117752.jpg"}},{"id":523251084,"name":"The Vale of Shadows","dt":362927,"ar":{"id":1124210,"name":"GUNSHIP"},"al":{"id":36950017,"name":"The Rise of the Synths (The Official Companion Album) ","picUrl":"https://p1.music.126.net/5nK6KmQU7AiCR_mmzdb8pQ==/109951163081146460.jpg"}},{"id":40157306,"name":"Black Sun on the Horizon","dt":287116,"ar":{"id":1124210,"name":"GUNSHIP"},"al":{"id":3439370,"name":"GUNSHIP","picUrl":"https://p1.music.126.net/5cpUzAuspDNqn5yeKl3uVA==/109951163787117752.jpg"}},{"id":40157307,"name":"The Hegemon","dt":232067,"ar":{"id":1124210,"name":"GUNSHIP"},"al":{"id":3439370,"name":"GUNSHIP","picUrl":"https://p2.music.126.net/5cpUzAuspDNqn5yeKl3uVA==/109951163787117752.jpg"}},{"id":1361040241,"name":"Cthulhu","dt":373346,"ar":{"id":1124210,"name":"GUNSHIP"},"al":{"id":78744094,"name":"Fangoria Presents: Hollydoom (Original Magazine Soundtrack)","picUrl":"https://p1.music.126.net/ZVNErdh30w_wzMOFyTUCWQ==/109951164021965074.jpg"}},{"id":40157304,"name":"Pink Mist","dt":242363,"ar":{"id":1124210,"name":"GUNSHIP"},"al":{"id":3439370,"name":"GUNSHIP","picUrl":"https://p2.music.126.net/5cpUzAuspDNqn5yeKl3uVA==/109951163787117752.jpg"}},{"id":1487185485,"name":"Eleanor Rigby","dt":177906,"ar":{"id":1124210,"name":"GUNSHIP"},"al":{"id":96821065,"name":"Eleanor Rigby","picUrl":"https://p2.music.126.net/aXf4eSZPS7du-ylUS_mRww==/109951165391012119.jpg"}},{"id":1854373138,"name":"Berserker","dt":334994,"ar":{"id":1124210,"name":"GUNSHIP"},"al":{"id":129231202,"name":"Berserker","picUrl":"https://p1.music.126.net/nhaTtoBN3f3S-YvO59uQpQ==/109951166098733940.jpg"}}]