[{"id":484048141,"name":"Whisky Prozak","dt":135000,"ar":{"id":1181033,"name":"Gero"},"al":{"id":35620353,"name":"Hypercut, Vol. 02","picUrl":"https://p2.music.126.net/x-DtiHMUVwjZqXzesRl9UQ==/17785700091326010.jpg"}},{"id":1342361506,"name":"Costa del Sol","dt":353613,"ar":{"id":1181033,"name":"Gero"},"al":{"id":75344068,"name":"Balaton Grooves 02","picUrl":"https://p2.music.126.net/NItIS_YdaF9KPXbMBzJqzg==/109951163821215608.jpg"}},{"id":1342418958,"name":"Costa del Sol","dt":353613,"ar":{"id":1181033,"name":"Gero"},"al":{"id":75345790,"name":"Chill House - Deep Inside Myself","picUrl":"https://p2.music.126.net/lsA3Y-ls18tSCymrtThQqA==/109951163821707439.jpg"}},{"id":1342728282,"name":"Costa del Sol","dt":353613,"ar":{"id":1181033,"name":"Gero"},"al":{"id":75360189,"name":"Havana Groove Vol. 1 - The Latin, Cuban & Brazilian Flavour","picUrl":"https://p2.music.126.net/5cQl5t3VxFPZctmau5m4Ew==/109951163825352167.jpg"}},{"id":1342747790,"name":"Costa del Sol","dt":353613,"ar":{"id":1181033,"name":"Gero"},"al":{"id":75362672,"name":"Brasil House Vol. 2 - Selected House Sounds From The Copa","picUrl":"https://p1.music.126.net/FCFEdcyDBY2ad4c07lv4gw==/109951163825569986.jpg"}},{"id":1334454591,"name":"Fell","dt":267731,"ar":{"id":33679,"name":"Fernando Lima"},"al":{"id":74937202,"name":"Fell","picUrl":"https://p1.music.126.net/2gVkN-YyzKuDia6aTuZjBg==/109951164747996969.jpg"}},{"id":1341122611,"name":"Vorovka","dt":214909,"ar":{"id":1181033,"name":"Gero"},"al":{"id":75270341,"name":"Old Songs","picUrl":"https://p2.music.126.net/x9mYEkSz0e_nsgvxqXWOPA==/109951163807453442.jpg"}},{"id":1341122612,"name":"Hey Hey","dt":163578,"ar":{"id":1181033,"name":"Gero"},"al":{"id":75270341,"name":"Old Songs","picUrl":"https://p1.music.126.net/x9mYEkSz0e_nsgvxqXWOPA==/109951163807453442.jpg"}},{"id":1341135032,"name":"Mari-Xuana","dt":122775,"ar":{"id":1181033,"name":"Gero"},"al":{"id":75270341,"name":"Old Songs","picUrl":"https://p2.music.126.net/x9mYEkSz0e_nsgvxqXWOPA==/109951163807453442.jpg"}},{"id":1332887586,"name":"Наркотик мой кайф","dt":198478,"ar":{"id":1181033,"name":"Gero"},"al":{"id":74856475,"name":"Наркотик мой кайф","picUrl":"https://p2.music.126.net/zBUuekNAQrFf_-aB5iXi_A==/109951163721359564.jpg"}},{"id":1332790514,"name":"Tonight","dt":146573,"ar":{"id":1181033,"name":"Gero"},"al":{"id":74848905,"name":"Tonight","picUrl":"https://p1.music.126.net/lkx1fZviUlJsBOZ0bufEHw==/109951163721079972.jpg"}},{"id":1332749684,"name":"Dont Know Why","dt":135148,"ar":{"id":1181033,"name":"Gero"},"al":{"id":74846407,"name":"The Night","picUrl":"https://p1.music.126.net/Bemvpr8EthG0Pi-f1juenQ==/109951163720660699.jpg"}},{"id":1332749685,"name":"Let - The","dt":135053,"ar":{"id":1181033,"name":"Gero"},"al":{"id":74846407,"name":"The Night","picUrl":"https://p1.music.126.net/Bemvpr8EthG0Pi-f1juenQ==/109951163720660699.jpg"}},{"id":1332749686,"name":"The Night","dt":141923,"ar":{"id":1181033,"name":"Gero"},"al":{"id":74846407,"name":"The Night","picUrl":"https://p2.music.126.net/Bemvpr8EthG0Pi-f1juenQ==/109951163720660699.jpg"}},{"id":1332751573,"name":"Crazy Girl by Me","dt":137500,"ar":{"id":1181033,"name":"Gero"},"al":{"id":74846407,"name":"The Night","picUrl":"https://p2.music.126.net/Bemvpr8EthG0Pi-f1juenQ==/109951163720660699.jpg"}},{"id":1332751574,"name":"Lady","dt":120418,"ar":{"id":1181033,"name":"Gero"},"al":{"id":74846407,"name":"The Night","picUrl":"https://p2.music.126.net/Bemvpr8EthG0Pi-f1juenQ==/109951163720660699.jpg"}},{"id":1332668597,"name":"Chemi Ocneba Xar","dt":283977,"ar":{"id":1181033,"name":"Gero"},"al":{"id":74841330,"name":"Chemi Ocneba Xar","picUrl":"https://p1.music.126.net/WeAwSkK2JYxQiGHKTeuUfA==/109951163720041822.jpg"}},{"id":1332675498,"name":"Cudi Bichi Var (Eric ERtives Version)","dt":196414,"ar":{"id":1181033,"name":"Gero"},"al":{"id":74842055,"name":"Cudi Bichi Var (Eric ERtives Version)","picUrl":"https://p1.music.126.net/jHYNGuUgwPSEA9jrEOu3Gw==/109951163720080438.jpg"}},{"id":1332697047,"name":"Am Gamit Shentan Minda","dt":214151,"ar":{"id":1181033,"name":"Gero"},"al":{"id":74844652,"name":"Am Gamit Shentan Minda","picUrl":"https://p2.music.126.net/qP0qwy3gqfb9iFD62c2VNg==/109951163720218864.jpg"}},{"id":1332711749,"name":"Lost Love","dt":140956,"ar":{"id":1181033,"name":"Gero"},"al":{"id":74845067,"name":"Lost Love","picUrl":"https://p2.music.126.net/BWd_2krc8oS6fPgTCFMdIA==/109951163720309858.jpg"}},{"id":1332718778,"name":"Black Rose (feat. Veronika Kvernadze)","dt":174027,"ar":{"id":1181033,"name":"Gero"},"al":{"id":74845266,"name":"Black Rose (feat. Veronika Kvernadze)","picUrl":"https://p1.music.126.net/7YdAGqwRkc-tRXhcdJ9fGQ==/109951163720365371.jpg"}},{"id":1332749485,"name":"With Me","dt":172117,"ar":{"id":1181033,"name":"Gero"},"al":{"id":74846888,"name":"With Me","picUrl":"https://p1.music.126.net/e1HelOYJFxk8H495CeFxoA==/109951163720640377.jpg"}},{"id":1318514152,"name":"No Quiero Quererte","dt":209888,"ar":{"id":30312257,"name":"Pasto Seco"},"al":{"id":73950088,"name":"Superestelar","picUrl":"https://p1.music.126.net/d0B2FEQqTu6gic_k724t3Q==/109951166173960067.jpg"}},{"id":1318514153,"name":"Me Dejaste Solo","dt":204615,"ar":{"id":30312257,"name":"Pasto Seco"},"al":{"id":73950088,"name":"Superestelar","picUrl":"https://p2.music.126.net/d0B2FEQqTu6gic_k724t3Q==/109951166173960067.jpg"}},{"id":1318514159,"name":"A la Orilla del Mar","dt":206693,"ar":{"id":30312257,"name":"Pasto Seco"},"al":{"id":73950088,"name":"Superestelar","picUrl":"https://p1.music.126.net/d0B2FEQqTu6gic_k724t3Q==/109951166173960067.jpg"}},{"id":1332815211,"name":"Today","dt":215902,"ar":{"id":1181033,"name":"Gero"},"al":{"id":74850443,"name":"Today","picUrl":"https://p1.music.126.net/T92G-A38-5T-m5qWn_TgmA==/109951163721214177.jpg"}},{"id":1332815210,"name":"Hello My Girl","dt":141505,"ar":{"id":1181033,"name":"Gero"},"al":{"id":74850442,"name":"Hello My Girl","picUrl":"https://p2.music.126.net/Jd30W3nRGyTDUgpubBxnFw==/109951163721214172.jpg"}},{"id":1332891265,"name":"Its Rain (Remix)","dt":138370,"ar":{"id":1181033,"name":"Gero"},"al":{"id":74857622,"name":"Its Rain (Remix)","picUrl":"https://p2.music.126.net/NkWKueOn6YSE7wCZXIojyg==/109951163721386655.jpg"}},{"id":1332891972,"name":"Ar Kitxo","dt":143673,"ar":{"id":1181033,"name":"Gero"},"al":{"id":74857138,"name":"Super-Star (Old School)","picUrl":"https://p1.music.126.net/8vW-Ry2HCLwHi6a0VLlyPA==/109951163721426640.jpg"}},{"id":1332891973,"name":"Superstar","dt":138605,"ar":{"id":1181033,"name":"Gero"},"al":{"id":74857138,"name":"Super-Star (Old School)","picUrl":"https://p1.music.126.net/8vW-Ry2HCLwHi6a0VLlyPA==/109951163721426640.jpg"}},{"id":1332891974,"name":"Tango Ovlshi","dt":187167,"ar":{"id":1181033,"name":"Gero"},"al":{"id":74857138,"name":"Super-Star (Old School)","picUrl":"https://p1.music.126.net/8vW-Ry2HCLwHi6a0VLlyPA==/109951163721426640.jpg"}},{"id":1332891975,"name":"Cudi Var Da","dt":137900,"ar":{"id":1181033,"name":"Gero"},"al":{"id":74857138,"name":"Super-Star (Old School)","picUrl":"https://p1.music.126.net/8vW-Ry2HCLwHi6a0VLlyPA==/109951163721426640.jpg"}},{"id":1332894204,"name":"QuTaisi","dt":207281,"ar":{"id":1181033,"name":"Gero"},"al":{"id":74857138,"name":"Super-Star (Old School)","picUrl":"https://p1.music.126.net/8vW-Ry2HCLwHi6a0VLlyPA==/109951163721426640.jpg"}},{"id":1332894205,"name":"My Gun","dt":121991,"ar":{"id":1181033,"name":"Gero"},"al":{"id":74857138,"name":"Super-Star (Old School)","picUrl":"https://p2.music.126.net/8vW-Ry2HCLwHi6a0VLlyPA==/109951163721426640.jpg"}},{"id":1332894206,"name":"Ou Ra Qalia","dt":145368,"ar":{"id":1181033,"name":"Gero"},"al":{"id":74857138,"name":"Super-Star (Old School)","picUrl":"https://p1.music.126.net/8vW-Ry2HCLwHi6a0VLlyPA==/109951163721426640.jpg"}},{"id":36307163,"name":"침대에서 ","dt":216868,"ar":{"id":1181033,"name":"Gero"},"al":{"id":3395062,"name":"침대에서","picUrl":"https://p1.music.126.net/xi9qJsm8szpZik3Sm8duMQ==/3253454909115141.jpg"}},{"id":517565075,"name":"낯선 너에게...","dt":198325,"ar":{"id":1181033,"name":"Gero"},"al":{"id":36753022,"name":"낯선 너에게...","picUrl":"https://p1.music.126.net/iJZ4xMj40_-mNXnmmGg7wQ==/109951163057951647.jpg"}},{"id":1340001779,"name":"상상","dt":227866,"ar":{"id":1181033,"name":"Gero"},"al":{"id":75137159,"name":"상상","picUrl":"https://p1.music.126.net/7nRZpv0Obll_4EKzdx5log==/109951163802125748.jpg"}},{"id":570332101,"name":"Pruebame","dt":217919,"ar":{"id":104700,"name":"Various Artists"},"al":{"id":39536027,"name":"Super Reggaeton Compilation - 19 Big Reggaeton Hits","picUrl":"https://p2.music.126.net/TAy9CUiOtnW10z8BkAstNQ==/109951163327334677.jpg"}},{"id":1318509595,"name":"No Quiero Quererte","dt":209888,"ar":{"id":30312257,"name":"Pasto Seco"},"al":{"id":73950764,"name":"No Quiero Quererte","picUrl":"https://p2.music.126.net/VCGYpeDGni6bDrutrWGg4A==/109951163608696728.jpg"}},{"id":1327870491,"name":"Fell","dt":267731,"ar":{"id":33679,"name":"Fernando Lima"},"al":{"id":74550593,"name":"BLCKNDWHT Pres. #Deephousehasnocolour 02","picUrl":"https://p2.music.126.net/1CigGJSfue94Xg26csuVyw==/109951164871128208.jpg"}}]