[{"id":417250727,"name":"Sorry","dt":182729,"ar":{"id":12054568,"name":"Ider"},"al":{"id":34738309,"name":"Sorry","picUrl":"https://p1.music.126.net/ZWo_ASssKIbgwp16D2M0HQ==/109951165109521392.jpg"}},{"id":416552640,"name":"Pulse","dt":215131,"ar":{"id":12054568,"name":"Ider"},"al":{"id":34735148,"name":"Pulse","picUrl":"https://p2.music.126.net/xWI3HTGDPe1K43R1t4PTMA==/109951165111455900.jpg"}},{"id":449578839,"name":"King Ruby","dt":220051,"ar":{"id":12054568,"name":"Ider"},"al":{"id":35093184,"name":"King Ruby","picUrl":"https://p1.music.126.net/UyW-z4wzu_9zjBcl5vAz9w==/109951165111457849.jpg"}},{"id":1362232705,"name":"Wu Baby","dt":219520,"ar":{"id":12054568,"name":"Ider"},"al":{"id":79914607,"name":"Emotional Education","picUrl":"https://p1.music.126.net/a3ZXSzxRTGOWnOodlmcH_g==/109951164162536203.jpg"}},{"id":462688246,"name":"Face On","dt":223007,"ar":{"id":12054568,"name":"Ider"},"al":{"id":35233048,"name":"Face On","picUrl":"https://p1.music.126.net/tr6SAWMQry9b0LbRalq6aw==/19025949207041606.jpg"}},{"id":449577823,"name":"Million","dt":225000,"ar":{"id":12054568,"name":"Ider"},"al":{"id":35092258,"name":"Million","picUrl":"https://p2.music.126.net/XAqoBRO5QgKe86n72lc8sA==/109951165112500437.jpg"}},{"id":469272592,"name":"Does She Even Know","dt":237739,"ar":{"id":12054568,"name":"Ider"},"al":{"id":35326537,"name":"Gut Me Like An Animal","picUrl":"https://p2.music.126.net/F2Lc4Mls852Djo4AJMSRzQ==/109951165111460262.jpg"}},{"id":1343437788,"name":"Mirror","dt":218116,"ar":{"id":12054568,"name":"Ider"},"al":{"id":75403356,"name":"Mirror","picUrl":"https://p2.music.126.net/suvNpv44se2Twz8vbtqqkA==/109951163831959257.jpg"}},{"id":1334344540,"name":"Mirror (12welve Remix)","dt":204285,"ar":{"id":12054568,"name":"Ider"},"al":{"id":74930207,"name":"Mirror (12welve Remix)","picUrl":"https://p1.music.126.net/8j3As8fF2-XfoyVtZtF_aw==/109951163734689901.jpg"}},{"id":1343168863,"name":"Learn to Let Go (HOAX Remix)","dt":240000,"ar":{"id":12054568,"name":"Ider"},"al":{"id":75384331,"name":"Learn to Let Go (HOAX Remix)","picUrl":"https://p1.music.126.net/3-PBvaRrMiei2l3crzb3lQ==/109951163829583702.jpg"}},{"id":1343168928,"name":"Body Love","dt":221684,"ar":{"id":12054568,"name":"Ider"},"al":{"id":75384355,"name":"Body Love","picUrl":"https://p2.music.126.net/DMkI9ryf8iXrvwnjdecqUQ==/109951163829588193.jpg"}},{"id":469272593,"name":"Nevermind","dt":182397,"ar":{"id":12054568,"name":"Ider"},"al":{"id":35326537,"name":"Gut Me Like An Animal","picUrl":"https://p1.music.126.net/F2Lc4Mls852Djo4AJMSRzQ==/109951165111460262.jpg"}},{"id":469410495,"name":"Face On","dt":222952,"ar":{"id":12054568,"name":"Ider"},"al":{"id":35326537,"name":"Gut Me Like An Animal","picUrl":"https://p1.music.126.net/F2Lc4Mls852Djo4AJMSRzQ==/109951165111460262.jpg"}},{"id":1844332152,"name":"cbb to b sad","dt":268235,"ar":{"id":12054568,"name":"Ider"},"al":{"id":127266950,"name":"cbb to b sad","picUrl":"https://p2.music.126.net/mVH1pqH6Q1FWh5D-4AjZWA==/109951165971878711.jpg"}},{"id":1373137918,"name":"Brown Sugar","dt":216520,"ar":{"id":12054568,"name":"Ider"},"al":{"id":79914607,"name":"Emotional Education","picUrl":"https://p1.music.126.net/a3ZXSzxRTGOWnOodlmcH_g==/109951164162536203.jpg"}},{"id":1844339584,"name":"BORED","dt":210309,"ar":{"id":12054568,"name":"Ider"},"al":{"id":127269378,"name":"BORED","picUrl":"https://p1.music.126.net/6CAqNqdFv6YE2VInucuKfA==/109951165971961030.jpg"}},{"id":1343436840,"name":"You've Got Your Whole Life Ahead of You Baby","dt":225440,"ar":{"id":12054568,"name":"Ider"},"al":{"id":75402340,"name":"You've Got Your Whole Life Ahead of You Baby","picUrl":"https://p1.music.126.net/rnHod6vDYVPJd-rBq7VV3A==/109951163831962667.jpg"}},{"id":1373137919,"name":"Clinging to the Weekend","dt":218320,"ar":{"id":12054568,"name":"Ider"},"al":{"id":79914607,"name":"Emotional Education","picUrl":"https://p2.music.126.net/a3ZXSzxRTGOWnOodlmcH_g==/109951164162536203.jpg"}},{"id":1340206396,"name":"Brown Sugar","dt":216520,"ar":{"id":12054568,"name":"Ider"},"al":{"id":75209753,"name":"Brown Sugar","picUrl":"https://p2.music.126.net/flrt6yOT40CwDVng16OaEg==/109951163817777458.jpg"}},{"id":1373137920,"name":"Saddest Generation","dt":249986,"ar":{"id":12054568,"name":"Ider"},"al":{"id":79914607,"name":"Emotional Education","picUrl":"https://p2.music.126.net/a3ZXSzxRTGOWnOodlmcH_g==/109951164162536203.jpg"}},{"id":1844338318,"name":"obsessed","dt":296500,"ar":{"id":12054568,"name":"Ider"},"al":{"id":127269393,"name":"shame","picUrl":"https://p2.music.126.net/NoAQ6VPUx8_bbBY19BfKUg==/109951165971960118.jpg"}},{"id":1844338319,"name":"Midland's Guilt","dt":280967,"ar":{"id":12054568,"name":"Ider"},"al":{"id":127269393,"name":"shame","picUrl":"https://p1.music.126.net/NoAQ6VPUx8_bbBY19BfKUg==/109951165971960118.jpg"}},{"id":1373138532,"name":"Busy Being a Rockstar","dt":211880,"ar":{"id":12054568,"name":"Ider"},"al":{"id":79914607,"name":"Emotional Education","picUrl":"https://p2.music.126.net/a3ZXSzxRTGOWnOodlmcH_g==/109951164162536203.jpg"}},{"id":1373138533,"name":"Invincible","dt":224640,"ar":{"id":12054568,"name":"Ider"},"al":{"id":79914607,"name":"Emotional Education","picUrl":"https://p2.music.126.net/a3ZXSzxRTGOWnOodlmcH_g==/109951164162536203.jpg"}},{"id":1844339601,"name":"cbb to b sad","dt":268235,"ar":{"id":12054568,"name":"Ider"},"al":{"id":127269393,"name":"shame","picUrl":"https://p1.music.126.net/NoAQ6VPUx8_bbBY19BfKUg==/109951165971960118.jpg"}},{"id":1838553377,"name":"Estamo aqui (feat. El Frausto, Zarkoce & Ider)","dt":340729,"ar":{"id":37585106,"name":"BioUrbano"},"al":{"id":126205896,"name":"Estamo aqui (feat. El Frausto, Zarkoce & Ider)","picUrl":"https://p2.music.126.net/N0bAcE05YP9FNnPi83sRGw==/109951165905339778.jpg"}},{"id":1373138534,"name":"Swim","dt":202613,"ar":{"id":12054568,"name":"Ider"},"al":{"id":79914607,"name":"Emotional Education","picUrl":"https://p2.music.126.net/a3ZXSzxRTGOWnOodlmcH_g==/109951164162536203.jpg"}},{"id":1373138535,"name":"You've Got Your Whole Life Ahead of You Baby","dt":225440,"ar":{"id":12054568,"name":"Ider"},"al":{"id":79914607,"name":"Emotional Education","picUrl":"https://p2.music.126.net/a3ZXSzxRTGOWnOodlmcH_g==/109951164162536203.jpg"}},{"id":1844339603,"name":"BORED","dt":210309,"ar":{"id":12054568,"name":"Ider"},"al":{"id":127269393,"name":"shame","picUrl":"https://p2.music.126.net/NoAQ6VPUx8_bbBY19BfKUg==/109951165971960118.jpg"}},{"id":1373138536,"name":"Body Love","dt":221684,"ar":{"id":12054568,"name":"Ider"},"al":{"id":79914607,"name":"Emotional Education","picUrl":"https://p2.music.126.net/a3ZXSzxRTGOWnOodlmcH_g==/109951164162536203.jpg"}},{"id":1844339604,"name":"waiting 17 03","dt":161875,"ar":{"id":12054568,"name":"Ider"},"al":{"id":127269393,"name":"shame","picUrl":"https://p2.music.126.net/NoAQ6VPUx8_bbBY19BfKUg==/109951165971960118.jpg"}},{"id":1373138537,"name":"Slide","dt":249973,"ar":{"id":12054568,"name":"Ider"},"al":{"id":79914607,"name":"Emotional Education","picUrl":"https://p1.music.126.net/a3ZXSzxRTGOWnOodlmcH_g==/109951164162536203.jpg"}},{"id":1844339605,"name":"embarrassed","dt":225156,"ar":{"id":12054568,"name":"Ider"},"al":{"id":127269393,"name":"shame","picUrl":"https://p1.music.126.net/NoAQ6VPUx8_bbBY19BfKUg==/109951165971960118.jpg"}},{"id":1859743923,"name":"obsessed","dt":296500,"ar":{"id":12054568,"name":"Ider"},"al":{"id":130111259,"name":"obsessed","picUrl":"https://p2.music.126.net/N6cseYjQyBhT_5SyBZ196A==/109951166160374237.jpg"}},{"id":469410496,"name":"GMLAA","dt":99506,"ar":{"id":12054568,"name":"Ider"},"al":{"id":35326537,"name":"Gut Me Like An Animal","picUrl":"https://p1.music.126.net/F2Lc4Mls852Djo4AJMSRzQ==/109951165111460262.jpg"}},{"id":1343181494,"name":"Learn to Let Go","dt":198128,"ar":{"id":12054568,"name":"Ider"},"al":{"id":75385922,"name":"Learn to Let Go","picUrl":"https://p1.music.126.net/bN5pQeaOXElpPpVB-V2c4g==/109951163829637932.jpg"}},{"id":1296896290,"name":"You've Got Your Whole Life Ahead Of You Baby","dt":225488,"ar":{"id":12054568,"name":"Ider"},"al":{"id":72010825,"name":"You've Got Your Whole Life Ahead Of You Baby","picUrl":"https://p2.music.126.net/47pmqDaxR5LzjrEfKlVvJQ==/109951163428869427.jpg"}},{"id":1343181487,"name":"Body Love (HOAX Remix)","dt":240000,"ar":{"id":12054568,"name":"Ider"},"al":{"id":75385919,"name":"Body Love (HOAX Remix)","picUrl":"https://p1.music.126.net/PoeJNrBUgbTLzY6jNYyyeA==/109951163829639295.jpg"}},{"id":1343168876,"name":"Mirror (Honors Remix)","dt":265714,"ar":{"id":12054568,"name":"Ider"},"al":{"id":75385312,"name":"Mirror (Honors Remix)","picUrl":"https://p2.music.126.net/Rns0VeExIFkCrdjBeH0-qQ==/109951163829590008.jpg"}},{"id":1481728638,"name":"Does She Even Know (Mixed)","dt":222433,"ar":{"id":12054568,"name":"Ider"},"al":{"id":95858204,"name":"Café del Mar ChillWave 3 (Mixed)","picUrl":"https://p1.music.126.net/U4QJbqOidtom6VD99OlQQA==/109951165339606514.jpg"}},{"id":1373138531,"name":"Mirror","dt":218116,"ar":{"id":12054568,"name":"Ider"},"al":{"id":79914607,"name":"Emotional Education","picUrl":"https://p1.music.126.net/a3ZXSzxRTGOWnOodlmcH_g==/109951164162536203.jpg"}},{"id":1421324203,"name":"Todo pasa (feat. Ider)","dt":167354,"ar":{"id":832275,"name":"Urbano "},"al":{"id":85516422,"name":"Autorretrato","picUrl":"https://p2.music.126.net/9XEeEdt9QRjJCHobOl0Keg==/109951164681837429.jpg"}},{"id":1478914289,"name":"Saturday,","dt":260347,"ar":{"id":12054568,"name":"Ider"},"al":{"id":95346468,"name":"Saturday,","picUrl":"https://p2.music.126.net/GDe1qOIAArBhvVn7ChJV1w==/109951166472222520.jpg"}},{"id":1829673519,"name":"Cross Yourself","dt":194250,"ar":{"id":12054568,"name":"Ider"},"al":{"id":124539904,"name":"Cross Yourself","picUrl":"https://p1.music.126.net/1B0MfHEOvSKIVEoWjS6WWA==/109951165808168387.jpg"}},{"id":1844339600,"name":"Cross Yourself","dt":194250,"ar":{"id":12054568,"name":"Ider"},"al":{"id":127269393,"name":"shame","picUrl":"https://p1.music.126.net/NoAQ6VPUx8_bbBY19BfKUg==/109951165971960118.jpg"}},{"id":1844339602,"name":"Knocked Up","dt":269750,"ar":{"id":12054568,"name":"Ider"},"al":{"id":127269393,"name":"shame","picUrl":"https://p2.music.126.net/NoAQ6VPUx8_bbBY19BfKUg==/109951165971960118.jpg"}},{"id":1314813270,"name":"Learn To Let Go (HOAX Remix)","dt":240039,"ar":{"id":12054568,"name":"Ider"},"al":{"id":73751622,"name":"Learn To Let Go (HOAX Remix)","picUrl":"https://p1.music.126.net/O6_JAWZyx8j42hojClo2xg==/109951163876516884.jpg"}}]