[{"id":1827078886,"name":"Dhulahan Banawunga","dt":236588,"ar":{"id":12544672,"name":"Neha Sharma"},"al":{"id":124272004,"name":"Dhulahan Banawunga","picUrl":"https://p2.music.126.net/-odaSZ3yEOp-GzLYfVqDQQ==/109951165897657913.jpg"}},{"id":494580781,"name":"Nazar","dt":168750,"ar":{"id":12544672,"name":"Neha Sharma"},"al":{"id":35866481,"name":"Nazar","picUrl":"https://p1.music.126.net/Krh9Dg5LD5H4WmbW3Sst8A==/17776903998307057.jpg"}},{"id":1367396448,"name":"Tere Kol Yaara","dt":250826,"ar":{"id":13002204,"name":"Priyanka Singh"},"al":{"id":79376922,"name":"Tere Kol Yaara","picUrl":"https://p1.music.126.net/1taHYcLfjJhslLP2MCpDIw==/109951165398969276.jpg"}},{"id":1498108788,"name":"Lambo Car","dt":195652,"ar":{"id":12908057,"name":"Guri"},"al":{"id":98752216,"name":"Lambo Car","picUrl":"https://p2.music.126.net/yO7_JCFtOZhhhplcuQLc_Q==/109951165496213442.jpg"}},{"id":1883490326,"name":"Byah Ke Lejangi","dt":170710,"ar":{"id":12544672,"name":"Neha Sharma"},"al":{"id":134152370,"name":"Byah Ke Lejangi","picUrl":"https://p1.music.126.net/3MhYpFIZJZrdupYvIztcyw==/109951166479564658.jpg"}},{"id":567694880,"name":"Maahiya Ve","dt":329584,"ar":{"id":12544672,"name":"Neha Sharma"},"al":{"id":39360337,"name":"True Emotions - The Harjai","picUrl":"https://p1.music.126.net/gYGXNUQgPOF1D6diq6lSSg==/109951163316578317.jpg"}},{"id":1470684718,"name":"Peace of Her Mind","dt":222000,"ar":{"id":12544672,"name":"Neha Sharma"},"al":{"id":93898380,"name":"Peace of Her Mind","picUrl":"https://p2.music.126.net/jKgkXYKEhk3Ym_qkF62lUQ==/109951165230947446.jpg"}},{"id":540997374,"name":"Nakhre","dt":263588,"ar":{"id":12544672,"name":"Neha Sharma"},"al":{"id":37732365,"name":"Nakhre","picUrl":"https://p1.music.126.net/L7H9CSHO1wMtNcJkckADjQ==/109951166567630420.jpg"}},{"id":546014025,"name":"Jhanjran De Bor","dt":189767,"ar":{"id":12544672,"name":"Neha Sharma"},"al":{"id":37953571,"name":"Jhanjran De Bor","picUrl":"https://p2.music.126.net/QoLw7cfHFB0rHPWXGVqNiQ==/109951163193227756.jpg"}},{"id":1357807126,"name":"Wednesdays Without You","dt":275521,"ar":{"id":12544672,"name":"Neha Sharma"},"al":{"id":78424098,"name":"Wednesdays Without You","picUrl":"https://p2.music.126.net/80X6lIoIMDJNMOlUJEBpfA==/109951163988436124.jpg"}},{"id":1410047176,"name":"Chann Kitha","dt":279670,"ar":{"id":12544672,"name":"Neha Sharma"},"al":{"id":84133992,"name":"Chann Kitha","picUrl":"https://p2.music.126.net/0FNTW0lEiJwB1mRjuC2V-g==/109951164553733674.jpg"}},{"id":1410039637,"name":"Akh Kaashni","dt":242550,"ar":{"id":12544672,"name":"Neha Sharma"},"al":{"id":84133413,"name":"Akh Kaashni","picUrl":"https://p2.music.126.net/f2QbfE88EkFYxaztHJYmjw==/109951164553691145.jpg"}},{"id":1483470797,"name":"Kalyug Mein Shyam Ka Sahara Hai","dt":522606,"ar":{"id":14064100,"name":"Surjeet Singh"},"al":{"id":96172729,"name":"Kalyug Mein Shyam Ka Sahara Hai","picUrl":"https://p1.music.126.net/vIkvrYCH5yTkl4yopXV0bw==/109951165353881665.jpg"}},{"id":1810161201,"name":"Maine Bhang Ka Baagh Lagaya Re","dt":212297,"ar":{"id":46473963,"name":"Karan Pawla"},"al":{"id":121314313,"name":"Maine Bhang Ka Baagh Lagaya Re","picUrl":"https://p1.music.126.net/ADf_mZnuOEtF_ZOvZEViUA==/109951165612521861.jpg"}},{"id":1815825917,"name":"Sudhu Tumi Dorkare","dt":10080,"ar":{"id":12544672,"name":"Neha Sharma"},"al":{"id":122272805,"name":"Jodi Rekhe Dao","picUrl":"https://p2.music.126.net/zdbsylp_boD9tE0LzCFFTg==/109951166449619158.jpg"}},{"id":1851277955,"name":"Chora Ki Jawani Mere Man Khatke","dt":325311,"ar":{"id":12544672,"name":"Neha Sharma"},"al":{"id":128562475,"name":"Chora Ki Jawani Mere Man Khatke","picUrl":"https://p1.music.126.net/MZYjxgne-b8GGoR44XeUTA==/109951166067669193.jpg"}},{"id":1851264829,"name":"Sunn Chore Mera Husn Hai Dhaar Gadase Ki","dt":508354,"ar":{"id":48252620,"name":"Deepak Palar"},"al":{"id":128560613,"name":"Sunn Chore Mera Husn Hai Dhaar Gadase Ki","picUrl":"https://p2.music.126.net/HouzR9uc61hJCX-6bCo3vw==/109951166067568624.jpg"}},{"id":1848978804,"name":"Ho Uth Bol Mere Piya Rove Teri Byahi Hai","dt":374862,"ar":{"id":12544672,"name":"Neha Sharma"},"al":{"id":128163083,"name":"Ho Uth Bol Mere Piya Rove Teri Byahi Hai","picUrl":"https://p1.music.126.net/QcMkASJpF6yqJpptSbWrgQ==/109951166044565790.jpg"}},{"id":1848978352,"name":"Haath Jod Ke Arj Karu","dt":372680,"ar":{"id":48252610,"name":"Satpal Nadar"},"al":{"id":128164048,"name":"Haath Jod Ke Arj Karu","picUrl":"https://p1.music.126.net/b3Y8TjPcrYhTogg6R0vUKw==/109951166044564354.jpg"}},{"id":1848982898,"name":"Mhari Heer Ke Sarp Lada Tu Chalke Diye Dawayi","dt":492773,"ar":{"id":48252610,"name":"Satpal Nadar"},"al":{"id":128166027,"name":"Mhari Heer Ke Sarp Lada Tu Chalke Diye Dawayi","picUrl":"https://p1.music.126.net/9vPbs3kcoOtbv2JIotmE_g==/109951166044586799.jpg"}},{"id":1848984796,"name":"Chodke Aashik Ranjhe Nae","dt":372564,"ar":{"id":48252969,"name":"Kapil Choudhary"},"al":{"id":128166060,"name":"Chodke Aashik Ranjhe Nae","picUrl":"https://p1.music.126.net/JYzfAlIoFf57VpY6ZwcZmA==/109951166044590630.jpg"}},{"id":1852135966,"name":"Brahaman Blood","dt":220018,"ar":{"id":31267084,"name":"Naveen David"},"al":{"id":128760246,"name":"Brahaman Blood","picUrl":"https://p1.music.126.net/HnED-xiNmSFamc9ta371KQ==/109951166075886496.jpg"}},{"id":1873996541,"name":"Jee Le Zara","dt":221291,"ar":{"id":35478932,"name":"Jefferson Cornelius"},"al":{"id":132503369,"name":"Jee Le Zara","picUrl":"https://p2.music.126.net/nuLTRaQGTu7Djyb68cXC9g==/109951166336336790.jpg"}},{"id":1889374187,"name":"Teri Kripa Se Oo Mata","dt":366236,"ar":{"id":14064100,"name":"Surjeet Singh"},"al":{"id":135173926,"name":"Teri Kripa Se Oo Mata","picUrl":"https://p2.music.126.net/dEMUsusAqeJIrBo5kZkCCA==/109951166550577569.jpg"}},{"id":1861515432,"name":"Dil Ko Karar Aaya","dt":270071,"ar":{"id":417232,"name":"Saif"},"al":{"id":130426591,"name":"Lofi Songs","picUrl":"https://p1.music.126.net/M36kKw7Ex9Skw9uo2MIRvw==/109951166182216284.jpg"}},{"id":1367026709,"name":"More Jigra Me Aaye Bhookamp","dt":218028,"ar":{"id":12544672,"name":"Neha Sharma"},"al":{"id":79329991,"name":"Jism Ki Lat","picUrl":"https://p2.music.126.net/o_SPiN-IV-MQ7ubyAa-o8A==/109951165399436367.jpg"}},{"id":1367030384,"name":"Mere Lehenge Se Aaye Bhookamp","dt":218028,"ar":{"id":12544672,"name":"Neha Sharma"},"al":{"id":79329991,"name":"Jism Ki Lat","picUrl":"https://p1.music.126.net/o_SPiN-IV-MQ7ubyAa-o8A==/109951165399436367.jpg"}}]