[{"id":532027581,"name":"Benim Yarim Gelişinden Bellidir","dt":247720,"ar":{"id":13222484,"name":"Günal Tunalı"},"al":{"id":37366449,"name":"Türk Sanat Müziğinde Unutulmayanlar","picUrl":"https://p2.music.126.net/Mb_x0jAj8tIpZpd8z3xsHQ==/109951163113941456.jpg"}},{"id":532027582,"name":"Beklerim Bu Sahillerde","dt":309660,"ar":{"id":13222484,"name":"Günal Tunalı"},"al":{"id":37366449,"name":"Türk Sanat Müziğinde Unutulmayanlar","picUrl":"https://p1.music.126.net/Mb_x0jAj8tIpZpd8z3xsHQ==/109951163113941456.jpg"}},{"id":532027583,"name":"Açmam Açamam","dt":185459,"ar":{"id":13222484,"name":"Günal Tunalı"},"al":{"id":37366449,"name":"Türk Sanat Müziğinde Unutulmayanlar","picUrl":"https://p2.music.126.net/Mb_x0jAj8tIpZpd8z3xsHQ==/109951163113941456.jpg"}},{"id":532027584,"name":"Küçük Yaşta Aldım Sazı Elime","dt":195154,"ar":{"id":13222484,"name":"Günal Tunalı"},"al":{"id":37366449,"name":"Türk Sanat Müziğinde Unutulmayanlar","picUrl":"https://p1.music.126.net/Mb_x0jAj8tIpZpd8z3xsHQ==/109951163113941456.jpg"}},{"id":532027585,"name":"Yadeller Aldı Beni","dt":247333,"ar":{"id":13222484,"name":"Günal Tunalı"},"al":{"id":37366449,"name":"Türk Sanat Müziğinde Unutulmayanlar","picUrl":"https://p2.music.126.net/Mb_x0jAj8tIpZpd8z3xsHQ==/109951163113941456.jpg"}},{"id":532027586,"name":"Ada Sahillerinde Bekliyorum","dt":193860,"ar":{"id":13222484,"name":"Günal Tunalı"},"al":{"id":37366449,"name":"Türk Sanat Müziğinde Unutulmayanlar","picUrl":"https://p2.music.126.net/Mb_x0jAj8tIpZpd8z3xsHQ==/109951163113941456.jpg"}},{"id":532027587,"name":"Hem Okudum Hem Yazdım","dt":186751,"ar":{"id":13222484,"name":"Günal Tunalı"},"al":{"id":37366449,"name":"Türk Sanat Müziğinde Unutulmayanlar","picUrl":"https://p2.music.126.net/Mb_x0jAj8tIpZpd8z3xsHQ==/109951163113941456.jpg"}}]