[{"id":1310412434,"name":"BINGBIAN病变（Remix）","dt":346017,"ar":{"id":30000267,"name":"蔡耀轩"},"al":{"id":73294331,"name":"错乱","picUrl":"https://p2.music.126.net/4Xk5HDYz9Ax3-jHves2xJw==/109951164416413087.jpg"}},{"id":1340128424,"name":"口是心非（Remix）","dt":365335,"ar":{"id":30000267,"name":"蔡耀轩"},"al":{"id":75190897,"name":"好聚好散","picUrl":"https://p2.music.126.net/Z7hWv-j5HwrieuK0D9tL_A==/109951164678741269.jpg"}},{"id":1335230437,"name":"往后余生（Remix）","dt":133677,"ar":{"id":30000267,"name":"蔡耀轩"},"al":{"id":74960186,"name":"鲸死化成岛","picUrl":"https://p1.music.126.net/jIFx1_UbpFHI4lQ6IVewSA==/109951164679084707.jpg"}},{"id":1310413658,"name":"少一点天分（Remix）","dt":357783,"ar":{"id":30000267,"name":"蔡耀轩"},"al":{"id":73294331,"name":"错乱","picUrl":"https://p1.music.126.net/4Xk5HDYz9Ax3-jHves2xJw==/109951164416413087.jpg"}},{"id":1335230397,"name":"Apologize（Remix）","dt":138019,"ar":{"id":30000267,"name":"蔡耀轩"},"al":{"id":74958153,"name":"神秘组织","picUrl":"https://p1.music.126.net/o9rBxhL0_LuIs48851cLrQ==/109951164678878978.jpg"}},{"id":1310413720,"name":"失眠症（Remix）","dt":195082,"ar":{"id":30000267,"name":"蔡耀轩"},"al":{"id":73294331,"name":"错乱","picUrl":"https://p1.music.126.net/4Xk5HDYz9Ax3-jHves2xJw==/109951164416413087.jpg"}},{"id":1348359967,"name":"浪子回头（Remix）","dt":142910,"ar":{"id":30000267,"name":"蔡耀轩"},"al":{"id":75686833,"name":"浪子回头","picUrl":"https://p2.music.126.net/egbAaIb7B5i4ehDLC5HhoA==/109951164678116084.jpg"}},{"id":1310416243,"name":"可能否（Remix）","dt":295836,"ar":{"id":30000267,"name":"蔡耀轩"},"al":{"id":73294331,"name":"错乱","picUrl":"https://p2.music.126.net/4Xk5HDYz9Ax3-jHves2xJw==/109951164416413087.jpg"}},{"id":1841370995,"name":"大风吹（Remix）","dt":304466,"ar":{"id":30000267,"name":"蔡耀轩"},"al":{"id":122428199,"name":"来日方长","picUrl":"https://p2.music.126.net/eqaHaM0XTh5BLqkM9rG6AQ==/109951165687411352.jpg"}},{"id":1338227269,"name":"干物女（Remix）","dt":220844,"ar":{"id":30000267,"name":"蔡耀轩"},"al":{"id":75076771,"name":"我回忆中的你","picUrl":"https://p1.music.126.net/AjB39_hqsv13aoQMGlYGSQ==/109951164713236131.jpg"}},{"id":1346962387,"name":"出山（Remix）","dt":347894,"ar":{"id":30000267,"name":"蔡耀轩"},"al":{"id":75607078,"name":"出山","picUrl":"https://p2.music.126.net/MjHLz9TrIMSIwyHi_dYx2g==/109951166501518810.jpg"}},{"id":1896841683,"name":"删了吧（Remix）","dt":366416,"ar":{"id":30000267,"name":"蔡耀轩"},"al":{"id":136411317,"name":"突破常理的存在","picUrl":"https://p2.music.126.net/yp4hLDtF3gFI0Py_4QPfwQ==/109951166644519038.jpg"}},{"id":1338225776,"name":"我怎么这么好看（Remix）","dt":199111,"ar":{"id":30000267,"name":"蔡耀轩"},"al":{"id":75084661,"name":"超级电音","picUrl":"https://p2.music.126.net/tTVibeQlIFvvLEmUjanfZw==/109951164416631261.jpg"}},{"id":1366755867,"name":"像鱼（Remix）","dt":405514,"ar":{"id":30000267,"name":"蔡耀轩"},"al":{"id":79202514,"name":"像鱼","picUrl":"https://p2.music.126.net/oyIFZs_fIoP3StQnhIgdfQ==/109951164677999684.jpg"}},{"id":1842736866,"name":"Hai Phút Hơn（Remix）","dt":184945,"ar":{"id":30000267,"name":"蔡耀轩"},"al":{"id":74958153,"name":"神秘组织","picUrl":"https://p1.music.126.net/o9rBxhL0_LuIs48851cLrQ==/109951164678878978.jpg"}},{"id":1860578403,"name":"一百万个可能（Remix）","dt":361086,"ar":{"id":30000267,"name":"蔡耀轩"},"al":{"id":130098108,"name":"预知未来","picUrl":"https://p2.music.126.net/ykOrD7qrZGq4GGqpl0WYGw==/109951166159264332.jpg"}},{"id":1892272743,"name":"答案（Remix）","dt":385420,"ar":{"id":30000267,"name":"蔡耀轩"},"al":{"id":75076771,"name":"我回忆中的你","picUrl":"https://p1.music.126.net/AjB39_hqsv13aoQMGlYGSQ==/109951164713236131.jpg"}},{"id":1831529091,"name":"生生世世爱（Remix）","dt":296000,"ar":{"id":30000267,"name":"蔡耀轩"},"al":{"id":124912270,"name":"我的碎碎念念","picUrl":"https://p2.music.126.net/DolxsoBDHpU4_9qrd2b1ew==/109951165825926017.jpg"}},{"id":1881560970,"name":"是想你的声音啊（Remix）","dt":360725,"ar":{"id":30000267,"name":"蔡耀轩"},"al":{"id":123807646,"name":"三分糖","picUrl":"https://p2.music.126.net/OE-B5AeR9Dwd3L-m1D7rQA==/109951165780147976.jpg"}},{"id":1820171627,"name":"四季予你（Remix）","dt":337427,"ar":{"id":30000267,"name":"蔡耀轩"},"al":{"id":122939654,"name":"十九.","picUrl":"https://p1.music.126.net/07howqqZ4-BEDW0XvcMhYA==/109951165724484233.jpg"}},{"id":1852600107,"name":"娃娃脸（Remix）","dt":292798,"ar":{"id":30000267,"name":"蔡耀轩"},"al":{"id":128870512,"name":"归一","picUrl":"https://p1.music.126.net/tNezhLKKh5ctreUVJzg5wQ==/109951166080045875.jpg"}},{"id":1494176031,"name":"我曾（Remix）","dt":384312,"ar":{"id":30000267,"name":"蔡耀轩"},"al":{"id":98025287,"name":"一鹿有你","picUrl":"https://p1.music.126.net/SUbsXsA9UwQsysixUBg3NA==/109951165457851104.jpg"}},{"id":1852957558,"name":"红色高跟鞋（Remix）","dt":364336,"ar":{"id":30000267,"name":"蔡耀轩"},"al":{"id":128870512,"name":"归一","picUrl":"https://p2.music.126.net/tNezhLKKh5ctreUVJzg5wQ==/109951166080045875.jpg"}},{"id":1807004574,"name":"嗜好（Remix）","dt":334959,"ar":{"id":30000267,"name":"蔡耀轩"},"al":{"id":120845223,"name":"信仰·释放","picUrl":"https://p1.music.126.net/27_8o9WtgqzuOSu7lEoZbw==/109951165567329539.jpg"}},{"id":1825044385,"name":"阿拉斯加海湾（Remix）","dt":363033,"ar":{"id":30000267,"name":"蔡耀轩"},"al":{"id":123807646,"name":"三分糖","picUrl":"https://p2.music.126.net/OE-B5AeR9Dwd3L-m1D7rQA==/109951165780147976.jpg"}},{"id":1817127439,"name":"夏天的风（Remix）","dt":375790,"ar":{"id":30000267,"name":"蔡耀轩"},"al":{"id":122428199,"name":"来日方长","picUrl":"https://p2.music.126.net/eqaHaM0XTh5BLqkM9rG6AQ==/109951165687411352.jpg"}},{"id":1825044404,"name":"十年人间（Remix）","dt":418134,"ar":{"id":30000267,"name":"蔡耀轩"},"al":{"id":123807646,"name":"三分糖","picUrl":"https://p1.music.126.net/OE-B5AeR9Dwd3L-m1D7rQA==/109951165780147976.jpg"}},{"id":1833163555,"name":"到此为止（Remix）","dt":332317,"ar":{"id":30000267,"name":"蔡耀轩"},"al":{"id":120845223,"name":"信仰·释放","picUrl":"https://p1.music.126.net/27_8o9WtgqzuOSu7lEoZbw==/109951165567329539.jpg"}},{"id":1837799899,"name":"爱人错过（Remix）","dt":244543,"ar":{"id":30000267,"name":"蔡耀轩"},"al":{"id":120845223,"name":"信仰·释放","picUrl":"https://p2.music.126.net/27_8o9WtgqzuOSu7lEoZbw==/109951165567329539.jpg"}},{"id":1860578401,"name":"潮汐（Remix）","dt":278903,"ar":{"id":30000267,"name":"蔡耀轩"},"al":{"id":130098108,"name":"预知未来","picUrl":"https://p1.music.126.net/ykOrD7qrZGq4GGqpl0WYGw==/109951166159264332.jpg"}},{"id":1841369517,"name":"心似烟火（Remix）","dt":410884,"ar":{"id":30000267,"name":"蔡耀轩"},"al":{"id":122428199,"name":"来日方长","picUrl":"https://p2.music.126.net/eqaHaM0XTh5BLqkM9rG6AQ==/109951165687411352.jpg"}},{"id":1831533748,"name":"那女孩对我说（Remix）","dt":513759,"ar":{"id":30000267,"name":"蔡耀轩"},"al":{"id":124912270,"name":"我的碎碎念念","picUrl":"https://p1.music.126.net/DolxsoBDHpU4_9qrd2b1ew==/109951165825926017.jpg"}},{"id":1838313896,"name":"后继者（Remix）","dt":373076,"ar":{"id":30000267,"name":"蔡耀轩"},"al":{"id":74960186,"name":"鲸死化成岛","picUrl":"https://p1.music.126.net/jIFx1_UbpFHI4lQ6IVewSA==/109951164679084707.jpg"}},{"id":1886440227,"name":"命硬（Remix）","dt":287552,"ar":{"id":30000267,"name":"蔡耀轩"},"al":{"id":128683689,"name":"般若","picUrl":"https://p1.music.126.net/FkH_0WQkmwjWrEh0kUG_uQ==/109951166072076433.jpg"}},{"id":1861617003,"name":"出卖（Remix）","dt":321899,"ar":{"id":30000267,"name":"蔡耀轩"},"al":{"id":120439136,"name":"卦像","picUrl":"https://p2.music.126.net/LCWys-an218DxwNopwE8vA==/109951165544185752.jpg"}},{"id":1850209633,"name":"踏山河（Remix）","dt":364471,"ar":{"id":30000267,"name":"蔡耀轩"},"al":{"id":120845223,"name":"信仰·释放","picUrl":"https://p1.music.126.net/27_8o9WtgqzuOSu7lEoZbw==/109951165567329539.jpg"}},{"id":1850274584,"name":"最（Remix）","dt":453110,"ar":{"id":30000267,"name":"蔡耀轩"},"al":{"id":128301302,"name":"扭转乾坤","picUrl":"https://p1.music.126.net/GhGV09fnSRjdzP6ge2BmPw==/109951166050637515.jpg"}},{"id":1886440254,"name":"时光洪流（Remix）","dt":372240,"ar":{"id":30000267,"name":"蔡耀轩"},"al":{"id":128683689,"name":"般若","picUrl":"https://p1.music.126.net/FkH_0WQkmwjWrEh0kUG_uQ==/109951166072076433.jpg"}},{"id":1881858554,"name":"你的酒馆对我打了烊（Remix）","dt":424711,"ar":{"id":30000267,"name":"蔡耀轩"},"al":{"id":120439136,"name":"卦像","picUrl":"https://p2.music.126.net/LCWys-an218DxwNopwE8vA==/109951165544185752.jpg"}},{"id":1860841089,"name":"隔岸（Remix）","dt":322870,"ar":{"id":30000267,"name":"蔡耀轩"},"al":{"id":128301302,"name":"扭转乾坤","picUrl":"https://p1.music.126.net/GhGV09fnSRjdzP6ge2BmPw==/109951166050637515.jpg"}},{"id":1896840849,"name":"偏爱和例外（Remix）","dt":357697,"ar":{"id":30000267,"name":"蔡耀轩"},"al":{"id":136411317,"name":"突破常理的存在","picUrl":"https://p2.music.126.net/yp4hLDtF3gFI0Py_4QPfwQ==/109951166644519038.jpg"}},{"id":1862553564,"name":"猜不透（Remix）","dt":415586,"ar":{"id":30000267,"name":"蔡耀轩"},"al":{"id":123807646,"name":"三分糖","picUrl":"https://p2.music.126.net/OE-B5AeR9Dwd3L-m1D7rQA==/109951165780147976.jpg"}},{"id":1884482656,"name":"大雾（Remix）","dt":388798,"ar":{"id":30000267,"name":"蔡耀轩"},"al":{"id":128870512,"name":"归一","picUrl":"https://p2.music.126.net/tNezhLKKh5ctreUVJzg5wQ==/109951166080045875.jpg"}},{"id":1862262425,"name":"日不落（Remix）","dt":366475,"ar":{"id":30000267,"name":"蔡耀轩"},"al":{"id":98025287,"name":"一鹿有你","picUrl":"https://p2.music.126.net/SUbsXsA9UwQsysixUBg3NA==/109951165457851104.jpg"}},{"id":1865150446,"name":"银河与星斗（Remix）","dt":335673,"ar":{"id":30000267,"name":"蔡耀轩"},"al":{"id":122939654,"name":"十九.","picUrl":"https://p1.music.126.net/07howqqZ4-BEDW0XvcMhYA==/109951165724484233.jpg"}},{"id":1897859044,"name":"死性不改（Remix）","dt":352008,"ar":{"id":30000267,"name":"蔡耀轩"},"al":{"id":136411317,"name":"突破常理的存在","picUrl":"https://p1.music.126.net/yp4hLDtF3gFI0Py_4QPfwQ==/109951166644519038.jpg"}},{"id":1869146755,"name":"蜜雪冰城（Remix）","dt":205399,"ar":{"id":30000267,"name":"蔡耀轩"},"al":{"id":131730263,"name":"了了","picUrl":"https://p2.music.126.net/4DbhBD20CX5y3Pvt_1s9bQ==/109951166278864731.jpg"}},{"id":1881560972,"name":"年轮（Remix）","dt":384778,"ar":{"id":30000267,"name":"蔡耀轩"},"al":{"id":123807646,"name":"三分糖","picUrl":"https://p1.music.126.net/OE-B5AeR9Dwd3L-m1D7rQA==/109951165780147976.jpg"}},{"id":1877505185,"name":"放空（Remix）","dt":366538,"ar":{"id":30000267,"name":"蔡耀轩"},"al":{"id":133118011,"name":"绝境重生","picUrl":"https://p1.music.126.net/9zRnGrW62C5Yj-16qzLaNQ==/109951166377800003.jpg"}},{"id":1896824563,"name":"你就不要想起我（Remix）","dt":422038,"ar":{"id":30000267,"name":"蔡耀轩"},"al":{"id":74960186,"name":"鲸死化成岛","picUrl":"https://p2.music.126.net/jIFx1_UbpFHI4lQ6IVewSA==/109951164679084707.jpg"}}]