[{"id":1897411863,"name":"Shivers (feat. Jessi & SUNMI)","dt":207908,"ar":{"id":33184,"name":"Ed Sheeran"},"al":{"id":136502208,"name":"Shivers (feat. Jessi & SUNMI)","picUrl":"https://p1.music.126.net/O7uxObGDxDwJ8ba_4JIq6w==/109951166651181903.jpg"}},{"id":33333989,"name":"Photograph","dt":259000,"ar":{"id":33184,"name":"Ed Sheeran"},"al":{"id":3197848,"name":"Photograph","picUrl":"https://p2.music.126.net/QtVGLaVaHAShqJ9nhyj3yQ==/109951166347458047.jpg"}},{"id":1899742433,"name":"Merry Christmas","dt":208587,"ar":{"id":33184,"name":"Ed Sheeran"},"al":{"id":136882424,"name":"Merry Christmas","picUrl":"https://p2.music.126.net/k9XILWILHc2YGUkeepGQMg==/109951166677694936.jpg"}},{"id":29422008,"name":"I See Fire (Kygo Remix)","dt":316000,"ar":{"id":844410,"name":"Kygo"},"al":{"id":3018281,"name":"I See Fire (Kygo Remix)","picUrl":"https://p2.music.126.net/e_lYQRo40Vr5hc5p4V_dog==/6620159511469872.jpg"}},{"id":461332332,"name":"Shape Of You (MAKJ Remix)","dt":177600,"ar":{"id":725091,"name":"MAKJ"},"al":{"id":35188769,"name":"Shape Of You (MAKJ Remix)","picUrl":"https://p1.music.126.net/Ys-IgiR9VpT9Oc-HHXSO-A==/18782957139104159.jpg"}},{"id":30967328,"name":"Ellie","dt":261403,"ar":{"id":1051010,"name":"Eastside"},"al":{"id":3107041,"name":"Ellie","picUrl":"https://p2.music.126.net/G8dSLxPoeuNFGFR6ITUVrA==/7724069185577514.jpg"}},{"id":32408068,"name":"I See Cali ","dt":316000,"ar":{"id":844410,"name":"Kygo"},"al":{"id":3159564,"name":"I See Cali","picUrl":"https://p2.music.126.net/xBngu8O_mAbxWVD50s-gDw==/7770248674382938.jpg"}},{"id":1374489487,"name":"Beautiful People (feat. Khalid)","dt":197903,"ar":{"id":33184,"name":"Ed Sheeran"},"al":{"id":80048992,"name":"Beautiful People (feat. Khalid)","picUrl":"https://p2.music.126.net/8Ko_C05tQvGYZFZQircEbA==/109951164177475658.jpg"}},{"id":28953952,"name":"Kiss Me","dt":278413,"ar":{"id":33184,"name":"Ed Sheeran"},"al":{"id":2957141,"name":"The Vampire Diary Season 4","picUrl":"https://p2.music.126.net/pN0z9o1HjPi2wBZkPPLCOw==/8895049069098276.jpg"}}]